comed_prices/__init__.py
comed_prices/read.py
comed_prices/utils.py
comed_prices-0.0.6.dist-info/licenses/LICENSE
tests/__init__.py
comed_prices-0.0.6.dist-info/METADATA
comed_prices-0.0.6.dist-info/WHEEL
comed_prices-0.0.6.dist-info/top_level.txt
comed_prices-0.0.6.dist-info/RECORD
